evl_opt/__init__.py
evl_opt/cli/__init__.py
evl_opt/cli/opt.py
evl_opt/etc/__init__.py
evl_opt/etc/speakers/__init__.py
evl_opt/etc/speakers/JD2/CV.trajectcomps.json
evl_opt/etc/speakers/JD2/CVCcodaVcoda.trajectcomps.json
evl_opt/etc/speakers/JD2/CVCcodaVcoda_allnonVTP.bounds.json
evl_opt/etc/speakers/JD2/CVCcodaVcoda_allnonVTP_full.bounds.json
evl_opt/etc/speakers/JD2/CVCcodaVcoda_allnonVTP_minimal.bounds.json
evl_opt/etc/speakers/JD2/CVtau.interval.json
evl_opt/etc/speakers/JD2/Cb.bounds.json
evl_opt/etc/speakers/JD2/Cd.bounds.json
evl_opt/etc/speakers/JD2/Cg.bounds.json
evl_opt/etc/speakers/JD2/Cstd-glot.bounds.json
evl_opt/etc/speakers/JD2/Cstd-glot_nodur.bounds.json
evl_opt/etc/speakers/JD2/Cstd.bounds.json
evl_opt/etc/speakers/JD2/Cstd_nodur.bounds.json
evl_opt/etc/speakers/JD2/Cstd_notau.bounds.json
evl_opt/etc/speakers/JD2/Vstd.bounds.json
evl_opt/etc/speakers/JD2/Vstd_Cb-gl.bounds.json
evl_opt/etc/speakers/JD2/Vstd_Cb-glot.bounds.json
evl_opt/etc/speakers/JD2/Vstd_Cb.bounds.json
evl_opt/etc/speakers/JD2/Vstd_Cb_nodur.bounds.json
evl_opt/etc/speakers/JD2/Vstd_Cb_notau.bounds.json
evl_opt/etc/speakers/JD2/Vstd_Cd-glot.bounds.json
evl_opt/etc/speakers/JD2/Vstd_Cd.bounds.json
evl_opt/etc/speakers/JD2/Vstd_Cd_nodur.bounds.json
evl_opt/etc/speakers/JD2/Vstd_Cd_notau.bounds.json
evl_opt/etc/speakers/JD2/Vstd_Cg-gl.bounds.json
evl_opt/etc/speakers/JD2/Vstd_Cg-glot.bounds.json
evl_opt/etc/speakers/JD2/Vstd_Cg.bounds.json
evl_opt/etc/speakers/JD2/Vstd_Cg_nodur.bounds.json
evl_opt/etc/speakers/JD2/Vstd_Cg_notau.bounds.json
evl_opt/etc/speakers/JD2/Vstd_Cstd-glot.bounds.json
evl_opt/etc/speakers/JD2/Vstd_Cstd-glot2.bounds.json
evl_opt/etc/speakers/JD2/Vstd_Cstd.bounds.json
evl_opt/etc/speakers/JD2/Vstd_Cstd_new.bounds.json
evl_opt/etc/speakers/JD2/Vstd_Cstd_nodur.bounds.json
evl_opt/etc/speakers/JD2/Vstd_Cstd_notau.bounds.json
evl_opt/etc/speakers/JD2/Vstd_nodur.bounds.json
evl_opt/etc/speakers/JD2/Vstd_notau.bounds.json
evl_opt/etc/speakers/JD2/__init__.py
evoclearn_opt-0.19.6.dist-info/LICENSE
evoclearn_opt-0.19.6.dist-info/METADATA
evoclearn_opt-0.19.6.dist-info/WHEEL
evoclearn_opt-0.19.6.dist-info/entry_points.txt
evoclearn_opt-0.19.6.dist-info/top_level.txt
evoclearn_opt-0.19.6.dist-info/RECORD
