Metadata-Version: 2.1
Name: evoclearn-opt
Version: 0.19.6
Summary: Tools for Early Vocal Learning optimisation experiments.
Home-page: https://gitlab.com/evoc-learn-group/evoc-learn-opt
Author: The EVocLearn Group
Author-email: daniel.r.vanniekerk@gmail.com
License: UNKNOWN
Platform: UNKNOWN
Requires-Python: >=3.7
Requires-Dist: click
Requires-Dist: evoclearn-core (<0.19.0,>=0.18.6)
Requires-Dist: evoclearn-rec (<0.6.0,>=0.5.3)
Requires-Dist: hyperopt (==0.2.5)
Requires-Dist: nlopt (==2.7.0)
Provides-Extra: dev
Requires-Dist: ipython ; extra == 'dev'
Requires-Dist: matplotlib ; extra == 'dev'
